poreplex/__init__.py
poreplex/__main__.py
poreplex/alignment_writer.py
poreplex/barcoding.py
poreplex/basecall_albacore.py
poreplex/commandline.py
poreplex/csupport.cpython-36m-x86_64-linux-gnu.so
poreplex/dashboard.py
poreplex/fast5_file.py
poreplex/io.py
poreplex/keras_wrap.py
poreplex/pipeline.py
poreplex/polya.py
poreplex/signal_analyzer.py
poreplex/signal_loader.py
poreplex/utils.py
poreplex/worker_persistence.py
poreplex/kmer_models/COPYRIGHT
poreplex/kmer_models/LICENSE.md
poreplex/kmer_models/README.md
poreplex/kmer_models/r9.4_180mv_70bps_5mer_RNA/template_median69pA.model
poreplex/kmer_models/r9.4_200mv_70bps_5mer_RNA/template_median68pA.model
poreplex/presets/rna-r941.cfg
poreplex/presets/MIN106-RNA001/demux-tetra-r4.hdf5
poreplex/presets/MIN106-RNA001/scaler-r3.hdf5
poreplex-0.5.dist-info/entry_points.txt
poreplex-0.5.dist-info/top_level.txt
poreplex-0.5.dist-info/WHEEL
poreplex-0.5.dist-info/METADATA
poreplex-0.5.dist-info/RECORD
