Metadata-Version: 2.1
Name: poreplex
Version: 0.5
Summary: A versatile sequence read processor for nanopore direct RNA sequencing
Home-page: https://github.com/hyeshik/poreplex
Author: Hyeshik Chang
Author-email: hyeshik@snu.ac.kr
License: MIT
Download-URL: https://github.com/hyeshik/poreplex/releases
Keywords: nanopore,direct RNA sequencing,barcode,demultiplexing
Platform: UNKNOWN
Classifier: Development Status :: 3 - Alpha
Classifier: Environment :: Console
Classifier: Intended Audience :: Science/Research
Classifier: Intended Audience :: Healthcare Industry
Classifier: License :: OSI Approved :: MIT License
Classifier: Operating System :: POSIX
Classifier: Programming Language :: Python
Classifier: Topic :: Scientific/Engineering :: Bio-Informatics
Provides-Extra: full
Provides-Extra: live
Requires-Dist: PyYAML (>=3.0)
Requires-Dist: h5py (>=2.7.0)
Requires-Dist: mappy (>=2.10)
Requires-Dist: numpy (>=1.14)
Requires-Dist: pandas (>=0.22.0)
Requires-Dist: pomegranate (>=0.10)
Requires-Dist: progressbar33 (>=2.4)
Requires-Dist: pysam (>=0.14.0)
Requires-Dist: scipy (>=1.0)
Requires-Dist: urwid (>=2.0.0)
Requires-Dist: tensorflow (>=1.8.0)
Provides-Extra: full
Requires-Dist: inotify (>=0.2.9); extra == 'full'
Provides-Extra: live
Requires-Dist: inotify (>=0.2.9); extra == 'live'
